README.rst
setup.py
smosl_send
smosl/__init__.py
smosl.egg-info/PKG-INFO
smosl.egg-info/SOURCES.txt
smosl.egg-info/dependency_links.txt
smosl.egg-info/top_level.txt