Metadata-Version: 1.1
Name: smosl
Version: 0.1
Summary: System Monitoring Over SysLog
Home-page: https://github.com/martinslabber/smosl
Author: martinslabber
Author-email: UNKNOWN
License: UNKNOWN
Platform: OS Independent
Classifier: Development Status :: 4 - Beta
Classifier: Intended Audience :: Developers
Classifier: Operating System :: OS Independent
Classifier: Programming Language :: Python
